upldr_apilibs/__init__.py
upldr_apilibs/http_app.py
upldr_apilibs/http_utils.py
upldr_apilibs/index_data.py
upldr_apilibs-0.1.33.dist-info/METADATA
upldr_apilibs-0.1.33.dist-info/WHEEL
upldr_apilibs-0.1.33.dist-info/top_level.txt
upldr_apilibs-0.1.33.dist-info/RECORD
