Metadata-Version: 2.1
Name: upldr-apilibs
Version: 0.1.33
Summary: Upldr Library for apiserver
Home-page: https://github.com/gageleblanc/upldr
Author: Gage LeBlanc
Author-email: gleblanc@symnet.io
License: UNKNOWN
Platform: UNKNOWN
Classifier: Programming Language :: Python :: 3
Classifier: License :: OSI Approved :: GNU General Public License v3 (GPLv3)
Classifier: Operating System :: OS Independent
Requires-Dist: clilib (>=1.9.10)
